multilingual_rouge/__init__.py
multilingual_rouge/io.py
multilingual_rouge/rouge.py
multilingual_rouge/rouge_scorer.py
multilingual_rouge/scoring.py
multilingual_rouge/stemmers.py
multilingual_rouge/tokenization_wrapper.py
multilingual_rouge/tokenizers.py
multilingual_rouge/bengali_stemmer/__init__.py
multilingual_rouge/bengali_stemmer/parser.py
multilingual_rouge-0.0.1.dist-info/licenses/LICENSE
multilingual_rouge-0.0.1.dist-info/METADATA
multilingual_rouge-0.0.1.dist-info/WHEEL
multilingual_rouge-0.0.1.dist-info/top_level.txt
multilingual_rouge-0.0.1.dist-info/RECORD
