Metadata-Version: 2.4
Name: multilingual-rouge
Version: 0.0.1
Summary: A fork of Multilingual ROUGE (a fork of XL-Sum)
Author-email: Nandan Thakur <nandant@gmail.com>
License:                                  Apache License
Project-URL: Homepage, https://github.com/nthakur/multliingual-rouge
Keywords: ROUGE-L,Multilingual,XL-SUM
Classifier: Intended Audience :: Science/Research
Classifier: License :: OSI Approved :: Apache Software License
Classifier: Programming Language :: Python :: 3.10
Classifier: Programming Language :: Python :: 3.11
Classifier: Programming Language :: Python :: 3.12
Classifier: Topic :: Scientific/Engineering :: Artificial Intelligence
Requires-Python: >=3.6
License-File: LICENSE
Requires-Dist: TurkishStemmer
Requires-Dist: absl-py
Requires-Dist: nltk
Requires-Dist: numpy
Requires-Dist: six>=1.14
Requires-Dist: pythainlp
Requires-Dist: pyonmttok
Requires-Dist: jieba
Requires-Dist: fugashi[unidic]
Dynamic: license-file
